{"2002": {"03": {"INCAFTTX": [], "HOUSING": [], "FOODHOME": [], "FOODAWAY": [], "HEALTH": [], "ALCBEVG": [], "APPAREL": [], "TRANS": [], "ENTRTAIN": []}, "04": {"INCAFTTX": [], "HOUSING": [], "FOODHOME": [], "FOODAWAY": [], "HEALTH": [], "ALCBEVG": [], "APPAREL": [], "TRANS": [], "ENTRTAIN": []}, "05": {"INCAFTTX": [29119.0], "HOUSING": [9777.0], "FOODHOME": [2397.0], "FOODAWAY": [1725.0], "HEALTH": [1223.0], "ALCBEVG": [324.0], "APPAREL": [1369.0], "TRANS": [5365.0], "ENTRTAIN": [1246.0]}}, "2003": {"03": {"INCAFTTX": [69112.0], "HOUSING": [18960.0], "FOODHOME": [3667.0], "FOODAWAY": [2806.0], "HEALTH": [2773.0], "ALCBEVG": [487.0], "APPAREL": [2116.0], "TRANS": [10788.0], "ENTRTAIN": [2921.0]}, "04": {"INCAFTTX": [41951.0], "HOUSING": [9221.0], "FOODHOME": [3015.0], "FOODAWAY": [1837.0], "HEALTH": [3386.0], "ALCBEVG": [284.0], "APPAREL": [1253.0], "TRANS": [6708.0], "ENTRTAIN": [1901.0]}, "05": {"INCAFTTX": [28822.0], "HOUSING": [9886.0], "FOODHOME": [2489.0], "FOODAWAY": [1688.0], "HEALTH": [1218.0], "ALCBEVG": [337.0], "APPAREL": [1300.0], "TRANS": [4912.0], "ENTRTAIN": [1119.0]}}, "2004": {"03": {"INCAFTTX": [73104.0], "HOUSING": [19169.0], "FOODHOME": [3975.0], "FOODAWAY": [3121.0], "HEALTH": [2966.0], "ALCBEVG": [547.0], "APPAREL": [2346.0], "TRANS": [10703.0], "ENTRTAIN": [3029.0]}, "04": {"INCAFTTX": [45107.0], "HOUSING": [9786.0], "FOODHOME": [3188.0], "FOODAWAY": [2009.0], "HEALTH": [3582.0], "ALCBEVG": [386.0], "APPAREL": [1373.0], "TRANS": [6575.0], "ENTRTAIN": [2136.0]}, "05": {"INCAFTTX": [30748.0], "HOUSING": [10290.0], "FOODHOME": [2587.0], "FOODAWAY": [1796.0], "HEALTH": [1272.0], "ALCBEVG": [391.0], "APPAREL": [1416.0], "TRANS": [4975.0], "ENTRTAIN": [1210.0]}}, "2005": {"03": {"INCAFTTX": [78512.0], "HOUSING": [20956.0], "FOODHOME": [3872.0], "FOODAWAY": [3364.0], "HEALTH": [3060.0], "ALCBEVG": [530.0], "APPAREL": [2347.0], "TRANS": [11158.0], "ENTRTAIN": [3381.0]}, "04": {"INCAFTTX": [48733.0], "HOUSING": [10815.0], "FOODHOME": [3316.0], "FOODAWAY": [2313.0], "HEALTH": [3773.0], "ALCBEVG": [323.0], "APPAREL": [1510.0], "TRANS": [7380.0], "ENTRTAIN": [2101.0]}, "05": {"INCAFTTX": [32916.0], "HOUSING": [10838.0], "FOODHOME": [2475.0], "FOODAWAY": [1839.0], "HEALTH": [1314.0], "ALCBEVG": [351.0], "APPAREL": [1516.0], "TRANS": [5382.0], "ENTRTAIN": [1286.0]}}, "2006": {"03": {"INCAFTTX": [81405.0], "HOUSING": [22570.0], "FOODHOME": [4017.0], "FOODAWAY": [3367.0], "HEALTH": [3102.0], "ALCBEVG": [612.0], "APPAREL": [2328.0], "TRANS": [11440.0], "ENTRTAIN": [3261.0]}, "04": {"INCAFTTX": [49148.0], "HOUSING": [11478.0], "FOODHOME": [3265.0], "FOODAWAY": [2374.0], "HEALTH": [3975.0], "ALCBEVG": [386.0], "APPAREL": [1520.0], "TRANS": [7332.0], "ENTRTAIN": [2203.0]}, "05": {"INCAFTTX": [34016.0], "HOUSING": [11787.0], "FOODHOME": [2651.0], "FOODAWAY": [1946.0], "HEALTH": [1431.0], "ALCBEVG": [405.0], "APPAREL": [1475.0], "TRANS": [5511.0], "ENTRTAIN": [1322.0]}}, "2007": {"03": {"INCAFTTX": [84691.0], "HOUSING": [23018.0], "FOODHOME": [4087.0], "FOODAWAY": [3436.0], "HEALTH": [3272.0], "ALCBEVG": [548.0], "APPAREL": [2351.0], "TRANS": [11499.0], "ENTRTAIN": [3690.0]}, "04": {"INCAFTTX": [53902.0], "HOUSING": [12368.0], "FOODHOME": [3333.0], "FOODAWAY": [2218.0], "HEALTH": [4087.0], "ALCBEVG": [415.0], "APPAREL": [1572.0], "TRANS": [8118.0], "ENTRTAIN": [2560.0]}, "05": {"INCAFTTX": [34583.0], "HOUSING": [12141.0], "FOODHOME": [2678.0], "FOODAWAY": [1895.0], "HEALTH": [1441.0], "ALCBEVG": [355.0], "APPAREL": [1438.0], "TRANS": [5608.0], "ENTRTAIN": [1452.0]}}, "2008": {"03": {"INCAFTTX": [86233.0], "HOUSING": [23382.0], "FOODHOME": [4385.0], "FOODAWAY": [3372.0], "HEALTH": [3489.0], "ALCBEVG": [543.0], "APPAREL": [2196.0], "TRANS": [11269.0], "ENTRTAIN": [3875.0]}, "04": {"INCAFTTX": [54150.0], "HOUSING": [12525.0], "FOODHOME": [3656.0], "FOODAWAY": [2327.0], "HEALTH": [4220.0], "ALCBEVG": [353.0], "APPAREL": [1574.0], "TRANS": [7995.0], "ENTRTAIN": [2524.0]}, "05": {"INCAFTTX": [36412.0], "HOUSING": [12479.0], "FOODHOME": [2918.0], "FOODAWAY": [2023.0], "HEALTH": [1435.0], "ALCBEVG": [366.0], "APPAREL": [1417.0], "TRANS": [5665.0], "ENTRTAIN": [1692.0]}}, "2009": {"03": {"INCAFTTX": [85062.0], "HOUSING": [22846.0], "FOODHOME": [4377.0], "FOODAWAY": [3306.0], "HEALTH": [3627.0], "ALCBEVG": [525.0], "APPAREL": [2085.0], "TRANS": [10005.0], "ENTRTAIN": [3578.0]}, "04": {"INCAFTTX": [52949.0], "HOUSING": [12287.0], "FOODHOME": [3837.0], "FOODAWAY": [2288.0], "HEALTH": [4478.0], "ALCBEVG": [370.0], "APPAREL": [1371.0], "TRANS": [7568.0], "ENTRTAIN": [2655.0]}, "05": {"INCAFTTX": [36637.0], "HOUSING": [12958.0], "FOODHOME": [2849.0], "FOODAWAY": [1904.0], "HEALTH": [1520.0], "ALCBEVG": [352.0], "APPAREL": [1466.0], "TRANS": [4849.0], "ENTRTAIN": [1588.0]}}, "2010": {"03": {"INCAFTTX": [86056.0], "HOUSING": [22278.0], "FOODHOME": [4215.0], "FOODAWAY": [3135.0], "HEALTH": [3734.0], "ALCBEVG": [519.0], "APPAREL": [2007.0], "TRANS": [10047.0], "ENTRTAIN": [3423.0]}, "04": {"INCAFTTX": [52334.0], "HOUSING": [12294.0], "FOODHOME": [3531.0], "FOODAWAY": [2184.0], "HEALTH": [4478.0], "ALCBEVG": [305.0], "APPAREL": [1321.0], "TRANS": [7450.0], "ENTRTAIN": [2513.0]}, "05": {"INCAFTTX": [36800.0], "HOUSING": [12843.0], "FOODHOME": [2902.0], "FOODAWAY": [1900.0], "HEALTH": [1518.0], "ALCBEVG": [338.0], "APPAREL": [1544.0], "TRANS": [5046.0], "ENTRTAIN": [1390.0]}}, "2011": {"03": {"INCAFTTX": [85962.0], "HOUSING": [22380.0], "FOODHOME": [4440.0], "FOODAWAY": [3227.0], "HEALTH": [4012.0], "ALCBEVG": [536.0], "APPAREL": [2014.0], "TRANS": [11039.0], "ENTRTAIN": [3390.0]}, "04": {"INCAFTTX": [54257.0], "HOUSING": [12653.0], "FOODHOME": [3963.0], "FOODAWAY": [2439.0], "HEALTH": [4564.0], "ALCBEVG": [427.0], "APPAREL": [1632.0], "TRANS": [7690.0], "ENTRTAIN": [2691.0]}, "05": {"INCAFTTX": [39107.0], "HOUSING": [13330.0], "FOODHOME": [3005.0], "FOODAWAY": [1991.0], "HEALTH": [1635.0], "ALCBEVG": [376.0], "APPAREL": [1474.0], "TRANS": [5567.0], "ENTRTAIN": [1533.0]}}}